{"version":"1.0.1","children":[{"name":"Project Quality","active":"true","type":"attribute","children":[{"name":"Ecosystem","type":"attribute","active":"true","children":[{"value":null,"mnemo":"QM_ACTIVITY","name":"Activity","type":"attribute","active":"true","children":[{"mnemo":"MLS_DEV_ACTIVITY","value":null,"type":"concept","name":"Developer ML activity","active":"true","children":[{"name":"Developer ML posts","active":"true","type":"metric","value":"52","mnemo":"MLS_DEV_VOL_1M"}]},{"value":null,"mnemo":"MLS_USR_ACTIVITY","children":[{"mnemo":"MLS_USR_VOL_1M","value":null,"type":"metric","name":"User ML posts","active":"true"}],"type":"concept","name":"User ML activity","active":"true"},{"value":null,"mnemo":"SCM_ACTIVITY","children":[{"mnemo":"SCM_COMMITS_1M","value":"0","type":"metric","name":"SCM Commits","active":"true"},{"value":"0","mnemo":"SCM_COMMITTED_FILES_1M","name":"Files committed","active":"true","type":"metric"}],"name":"SCM activity","active":"true","type":"concept"}]},{"value":null,"mnemo":"QM_DIVERSITY","children":[{"value":null,"mnemo":"MLS_DEV_ACTIVITY","children":[{"value":null,"mnemo":"MLS_DEV_AUTH_1M","type":"metric","name":"Developer ML authors","active":"true"}],"type":"concept","name":"Developer ML activity","active":"true"},{"mnemo":"MLS_USR_DIVERSITY","value":null,"children":[{"value":null,"mnemo":"MLS_USR_AUTH_1M","name":"User ML authors","active":"true","type":"metric"}],"type":"concept","name":"User ML diversity","active":"true"},{"type":"concept","name":"SCM diversity","active":"true","children":[{"value":"0","mnemo":"SCM_COMMITTERS_1M","name":"SCM committers","active":"true","type":"metric"}],"mnemo":"SCM_DIVERSITY","value":null}],"type":"attribute","name":"Diversity","active":"true"},{"children":[{"value":null,"mnemo":"MLS_DEV_RESPONSIVENESS","children":[{"value":null,"mnemo":"MLS_DEV_RESP_TIME_MED_1M","type":"metric","name":"Developer ML response time","active":"true"}],"name":"Developer ML responsiveness","active":"true","type":"concept"},{"value":null,"mnemo":"MLS_USR_RESPONSIVENESS","type":"concept","name":"User ML responsiveness","active":"true","children":[{"type":"metric","name":"User ML response time","active":"true","value":"0.56","mnemo":"MLS_USR_RESP_TIME_MED_1M"}]}],"type":"attribute","name":"Responsiveness","active":"true","mnemo":"QM_RESPONSIVENESS","value":null},{"type":"attribute","name":"Support","active":"true","children":[{"children":[{"type":"metric","name":"Developer ML response ratio","active":"true","mnemo":"MLS_DEV_RESP_RATIO_1M","value":"0.4444444444444444"},{"name":"Developer ML subjects","active":"true","type":"metric","value":"36","mnemo":"MLS_DEV_SUBJ_1M"}],"type":"concept","name":"Developer ML support","active":"true","value":null,"mnemo":"MLS_DEV_SUPPORT"},{"mnemo":"MLS_USR_SUPPORT","value":null,"children":[{"name":"User ML response ratio","active":"true","type":"metric","value":null,"mnemo":"MLS_USR_RESP_RATIO_1M"},{"type":"metric","name":"User ML subjects","active":"true","mnemo":"MLS_USR_SUBJ_1M","value":null}],"type":"concept","name":"User ML support","active":"true"}],"value":null,"mnemo":"QM_SUPPORT"},{"name":"Visibility","active":"false","type":"attribute","children":[{"value":null,"mnemo":"PUB_CONF","children":[{"mnemo":"PUB_CONF_VOL","value":null,"name":"Number of publications","active":"false","type":"metric"}],"name":"Visibility in research","active":"false","type":"concept"}],"mnemo":"QM_VISIBILITY","value":null},{"value":null,"mnemo":"QM_USAGE","children":[{"mnemo":"DOWNLOADS","value":null,"children":[{"value":"0","mnemo":"DL_REPO_1M","name":"Number of downloads on the web site","active":"false","type":"metric"},{"value":"0","mnemo":"DL_UPDATE_SITE_1M","name":"Number of downloads on update site","active":"false","type":"metric"}],"type":"concept","name":"Downloads","active":"false"},{"name":"Installations","active":"true","type":"concept","children":[{"mnemo":"SURVEY_INSTALL","value":null,"type":"metric","name":"Installation survey","active":"false"},{"mnemo":"MKT_INSTALL_SUCCESS_1M","value":"0","type":"metric","name":"Number of successfull installs on the Marketplace","active":"true"}],"value":null,"mnemo":"INSTALL"}],"name":"Usage","active":"true","type":"attribute"},{"name":"User feedback","active":"true","type":"attribute","children":[{"type":"concept","name":"Marketplace feedback","active":"true","children":[{"name":"Number of favourites on the Marketplace","active":"true","type":"metric","mnemo":"MKT_FAV","value":"0"}],"mnemo":"MKT_FEEDBACK","value":null}],"value":null,"mnemo":"QM_FEEDBACK"}],"mnemo":"QM_ECOSYSTEM","value":null},{"type":"attribute","name":"Process","active":"true","children":[{"mnemo":"QM_SCM","value":null,"type":"attribute","name":"Configuration Management","active":"true","children":[{"children":[{"type":"metric","name":"SCM information","active":"true","value":"0","mnemo":"PUB_SCM_INFO_PMI"}],"type":"concept","name":"SCM information access","active":"true","mnemo":"PUB_SCM_INFO","value":null},{"type":"concept","name":"SCM usage","active":"true","children":[{"value":"0","mnemo":"SCM_COMMITS_1M","name":"SCM Commits","active":"true","type":"metric"},{"name":"SCM committers","active":"true","type":"metric","mnemo":"SCM_COMMITTERS_1M","value":"0"}],"mnemo":"SCM_USAGE","value":null}]},{"value":null,"mnemo":"QM_ITS","children":[{"value":null,"mnemo":"PUB_ITS_INFO","name":"ITS information access","active":"true","type":"concept","children":[{"type":"metric","name":"ITS information","active":"true","mnemo":"PUB_ITS_INFO_PMI","value":"0"}]},{"children":[{"mnemo":"ITS_UPDATES_1M","value":"54","name":"ITS updates","active":"true","type":"metric"},{"value":"1","mnemo":"ITS_AUTH_1M","type":"metric","name":"ITS authors","active":"true"}],"type":"concept","name":"ITS usage","active":"true","value":null,"mnemo":"ITS_USAGE"}],"type":"attribute","name":"Change Management","active":"true"},{"value":null,"mnemo":"QM_IP","children":[{"mnemo":"LIC","value":null,"children":[{"name":"License identification","active":"false","type":"metric","value":null,"mnemo":"LIC_IDENT"}],"name":"Licensing","active":"false","type":"concept"},{"name":"IP Log","active":"false","type":"concept","children":[{"mnemo":"IP_LOG_COV","value":null,"name":"IP log code coverage","active":"false","type":"metric"}],"mnemo":"IP_LOG","value":null}],"type":"attribute","name":"Intellectual Property Management","active":"false"},{"type":"attribute","name":"Planning Management","active":"true","children":[{"mnemo":"PLAN_ON_TIME","value":null,"name":"Plan on time","active":"false","type":"concept","children":[{"mnemo":"PLAN_NEXT_MILESTONE","value":null,"name":"Project is on time for next milestone","active":"false","type":"metric"}]},{"mnemo":"PLAN_RELEASES","value":null,"children":[{"name":"Number of milestones","active":"true","type":"metric","value":"0","mnemo":"PLAN_MILESTONES_VOL"},{"value":"0","mnemo":"PLAN_REVIEWS_SUCCESS_RATE","name":"Milestone success rate","active":"true","type":"metric"}],"type":"concept","name":"Milestones","active":"true"}],"value":null,"mnemo":"QM_PLAN"},{"mnemo":"QM_TST","value":null,"children":[{"value":null,"mnemo":"TST_COV","type":"concept","name":"Test coverage","active":"true","children":[{"name":"Percentage of lines of code covered by tests","active":"true","type":"metric","mnemo":"TST_COV_LINES","value":null},{"mnemo":"TST_COV_BRANCHES","value":null,"type":"metric","name":"Percentage of branches covered by tests","active":"true"}]},{"type":"concept","name":"Number of tests","active":"true","children":[{"name":"Number of tests relative to the code size","active":"true","type":"metric","mnemo":"TST_VOL_IDX","value":null}],"mnemo":"TST_VOL","value":null},{"value":null,"mnemo":"TST_SUCCESS","type":"concept","name":"Test success density","active":"true","children":[{"name":"Test success density","active":"true","type":"metric","value":null,"mnemo":"TST_SUCCESS_LAST"}]}],"name":"Test Management","active":"true","type":"attribute"}],"mnemo":"QM_PROCESS","value":null},{"value":null,"mnemo":"QM_PRODUCT","type":"attribute","name":"Product","active":"true","children":[{"mnemo":"QM_ANA","value":null,"type":"attribute","name":"Analysability","active":"true","children":[{"type":"concept","name":"Code size","active":"true","children":[{"type":"metric","name":"Source Lines Of Code","active":"true","mnemo":"SLOC","value":null}],"mnemo":"CODE_SIZE","value":null},{"mnemo":"ALL_DATA","value":null,"name":"Access points","active":"false","type":"concept","children":[{"mnemo":"ATTRS","value":null,"type":"metric","name":"Average number of attributes","active":"false"},{"mnemo":"METHS","value":null,"name":"Average number of methods","active":"false","type":"metric"}]},{"value":null,"mnemo":"CPX","children":[{"name":"Average Cyclomatic Complexity","active":"true","type":"metric","mnemo":"VG","value":null},{"mnemo":"MDIT","value":null,"type":"metric","name":"Depth of Inheritance Tree","active":"false"}],"type":"concept","name":"Code complexity","active":"true"},{"value":null,"mnemo":"CODE_DOC","type":"concept","name":"Code documentation","active":"true","children":[{"mnemo":"COMR","value":null,"type":"metric","name":"Comment rate","active":"true"}]},{"mnemo":"PRACTICES_ANA","value":null,"type":"concept","name":"Analysability practices","active":"true","children":[{"type":"metric","name":"Average number of non-conformities for analysability","active":"true","value":null,"mnemo":"NCC_ANA_IDX"},{"mnemo":"ROKR_ANA","value":"66.6666666666667","type":"metric","name":"Adherence to analysability rules","active":"true"}]}]},{"children":[{"value":null,"mnemo":"PUBLIC_DATA","children":[{"name":"Average number of public attributes","active":"false","type":"metric","mnemo":"ATTRS_PUBLIC","value":null},{"mnemo":"METHS_PUBLIC","value":null,"type":"metric","name":"Average number of public methods","active":"false"}],"type":"concept","name":"Public access points","active":"false"},{"value":null,"mnemo":"CPX","children":[{"name":"Average Cyclomatic Complexity","active":"true","type":"metric","mnemo":"VG","value":null},{"name":"Depth of Inheritance Tree","active":"false","type":"metric","mnemo":"MDIT","value":null}],"name":"Code complexity","active":"true","type":"concept"},{"name":"Code cloning","active":"true","type":"concept","children":[{"type":"metric","name":"Cloning density","active":"true","value":null,"mnemo":"CLONE_IDX"}],"value":null,"mnemo":"CODE_CLONE"},{"name":"Changeability practices","active":"true","type":"concept","children":[{"mnemo":"NCC_CHA_IDX","value":null,"name":"Average number of non-conformities for changeability","active":"true","type":"metric"},{"value":"63.1578947368421","mnemo":"ROKR_CHA","name":"Adherence to changeability rules","type":"metric","active":"true"}],"mnemo":"PRACTICES_CHA","value":null}],"name":"Changeability","active":"true","type":"attribute","mnemo":"QM_CHA","value":null},{"type":"attribute","name":"Reliability","active":"true","children":[{"mnemo":"PUBLIC_DATA","value":null,"children":[{"name":"Average number of public attributes","active":"false","type":"metric","value":null,"mnemo":"ATTRS_PUBLIC"},{"type":"metric","name":"Average number of public methods","active":"false","value":null,"mnemo":"METHS_PUBLIC"}],"type":"concept","name":"Public access points","active":"false"},{"value":null,"mnemo":"CPX","name":"Code complexity","active":"true","type":"concept","children":[{"mnemo":"VG","value":null,"type":"metric","name":"Average Cyclomatic Complexity","active":"true"},{"mnemo":"MDIT","value":null,"type":"metric","name":"Depth of Inheritance Tree","active":"false"}]},{"type":"concept","name":"SCM Stability","active":"true","children":[{"value":null,"mnemo":"SCM_STABILITY_1M","type":"metric","name":"File stability index","active":"true"}],"value":null,"mnemo":"SCM_STABILITY"},{"children":[{"mnemo":"ITS_FIX_MED_1M","value":"0.0","name":"Median time to fix bug","active":"true","type":"metric"},{"name":"Number of open bugs","active":"true","type":"metric","mnemo":"ITS_BUGS_OPEN","value":null},{"value":"0.1370463764938055","mnemo":"ITS_BUGS_DENSITY","type":"metric","name":"Defect density","active":"true"}],"type":"concept","name":"ITS Reliability","active":"true","mnemo":"ITS_REL","value":null},{"name":"Reliability practices","active":"true","type":"concept","children":[{"mnemo":"NCC_REL_IDX","value":null,"type":"metric","name":"Average number of non-conformities for reliability","active":"true"},{"mnemo":"ROKR_REL","value":"76.5957446808511","type":"metric","name":"Adherence to reliability rules","active":"true"}],"value":null,"mnemo":"PRACTICES_REL"}],"mnemo":"QM_REL","value":null},{"children":[{"children":[{"value":null,"mnemo":"ATTRS_PUBLIC","type":"metric","name":"Average number of public attributes","active":"false"},{"mnemo":"METHS_PUBLIC","value":null,"name":"Average number of public methods","active":"false","type":"metric"}],"type":"concept","name":"Public access points","active":"false","mnemo":"PUBLIC_DATA","value":null},{"value":null,"mnemo":"TST_COV","children":[{"name":"Percentage of lines of code covered by tests","active":"true","type":"metric","mnemo":"TST_COV_LINES","value":null}],"name":"Test coverage","active":"true","type":"concept"},{"value":null,"mnemo":"CODE_DOC","name":"Code documentation","active":"true","type":"concept","children":[{"mnemo":"COMR","value":null,"type":"metric","name":"Comment rate","active":"true"}]},{"name":"Reusability practices","active":"true","type":"concept","children":[{"mnemo":"NCC_REU_IDX","value":null,"name":"Average number of non-conformities for reusability","active":"true","type":"metric"},{"type":"metric","name":"Adherence to reusability rules","active":"true","value":"55.5555555555556","mnemo":"ROKR_REU"}],"value":null,"mnemo":"PRACTICES_REU"}],"name":"Reusability","active":"true","type":"attribute","value":null,"mnemo":"QM_REU"}]}],"mnemo":"QM_QUALITY","value":null}],"name":"PolarSys Quality Model"}