{"version":"1.0.1","name":"PolarSys Quality Model","children":[{"children":[{"children":[{"children":[{"type":"concept","ind":null,"mnemo":"MLS_DEV_ACTIVITY","name":"Developer ML activity","m_total":"1","m_ok":"0","active":"true","children":[{"name":"Developer ML posts","mnemo":"MLS_DEV_VOL_1M","type":"metric","ind":null,"value":null,"active":"true","m_ok":"0","m_total":"1"}]},{"children":[{"active":"true","m_ok":"0","value":null,"m_total":"1","mnemo":"MLS_USR_VOL_1M","name":"User ML posts","ind":null,"type":"metric"}],"active":"true","m_ok":"0","m_total":"1","name":"User ML activity","mnemo":"MLS_USR_ACTIVITY","type":"concept","ind":null},{"m_ok":"2","active":"true","children":[{"m_total":"1","value":0,"active":"true","m_ok":"1","ind":1,"type":"metric","name":"SCM Commits","mnemo":"SCM_COMMITS_1M"},{"active":"true","value":0,"m_ok":"1","m_total":"1","mnemo":"SCM_COMMITTED_FILES_1M","name":"Files committed","type":"metric","ind":1}],"m_total":"2","mnemo":"SCM_ACTIVITY","name":"SCM activity","type":"concept","ind":1}],"m_ok":"2","active":"true","m_total":"4","name":"Activity","mnemo":"QM_ACTIVITY","type":"attribute","ind":1},{"m_total":"3","active":"true","m_ok":"1","children":[{"active":"true","m_ok":"0","children":[{"m_total":"1","active":"true","m_ok":"0","value":null,"type":"metric","ind":null,"mnemo":"MLS_DEV_AUTH_1M","name":"Developer ML authors"}],"m_total":"1","mnemo":"MLS_DEV_ACTIVITY","name":"Developer ML activity","ind":null,"type":"concept"},{"name":"User ML diversity","mnemo":"MLS_USR_DIVERSITY","ind":null,"type":"concept","children":[{"m_total":"1","active":"true","m_ok":"0","value":null,"ind":null,"type":"metric","mnemo":"MLS_USR_AUTH_1M","name":"User ML authors"}],"m_ok":"0","active":"true","m_total":"1"},{"ind":1,"type":"concept","name":"SCM diversity","mnemo":"SCM_DIVERSITY","m_total":"1","children":[{"active":"true","m_ok":"1","value":0,"m_total":"1","mnemo":"SCM_COMMITTERS_1M","name":"SCM committers","type":"metric","ind":1}],"active":"true","m_ok":"1"}],"type":"attribute","ind":1,"mnemo":"QM_DIVERSITY","name":"Diversity"},{"m_total":"2","m_ok":"0","active":"true","children":[{"mnemo":"MLS_DEV_RESPONSIVENESS","name":"Developer ML responsiveness","ind":null,"type":"concept","active":"true","m_ok":"0","children":[{"name":"Developer ML response time","mnemo":"MLS_DEV_RESP_TIME_MED_1M","ind":null,"type":"metric","value":null,"m_ok":"0","active":"true","m_total":"1"}],"m_total":"1"},{"m_total":"1","m_ok":"0","active":"true","children":[{"active":"true","m_ok":"0","value":null,"m_total":"1","mnemo":"MLS_USR_RESP_TIME_MED_1M","name":"User ML response time","type":"metric","ind":null}],"ind":null,"type":"concept","mnemo":"MLS_USR_RESPONSIVENESS","name":"User ML responsiveness"}],"ind":null,"type":"attribute","mnemo":"QM_RESPONSIVENESS","name":"Responsiveness"},{"children":[{"mnemo":"MLS_DEV_SUPPORT","name":"Developer ML support","type":"concept","ind":null,"active":"true","m_ok":"0","children":[{"active":"true","m_ok":"0","value":null,"m_total":"1","mnemo":"MLS_DEV_RESP_RATIO_1M","name":"Developer ML response ratio","type":"metric","ind":null},{"mnemo":"MLS_DEV_SUBJ_1M","name":"Developer ML subjects","type":"metric","ind":null,"value":null,"active":"true","m_ok":"0","m_total":"1"}],"m_total":"2"},{"ind":null,"type":"concept","mnemo":"MLS_USR_SUPPORT","name":"User ML support","m_total":"2","m_ok":"0","active":"true","children":[{"m_total":"1","value":null,"m_ok":"0","active":"true","ind":null,"type":"metric","mnemo":"MLS_USR_RESP_RATIO_1M","name":"User ML response ratio"},{"name":"User ML subjects","mnemo":"MLS_USR_SUBJ_1M","ind":null,"type":"metric","m_ok":"0","value":null,"active":"true","m_total":"1"}]}],"active":"true","m_ok":"0","m_total":"4","name":"Support","mnemo":"QM_SUPPORT","type":"attribute","ind":null},{"ind":null,"type":"attribute","name":"Visibility","mnemo":"QM_VISIBILITY","m_total":"1","children":[{"m_ok":"0","active":"false","children":[{"m_total":"1","active":"false","m_ok":"0","value":null,"type":"metric","ind":null,"name":"Number of publications","mnemo":"PUB_CONF_VOL"}],"m_total":"1","mnemo":"PUB_CONF","name":"Visibility in research","ind":null,"type":"concept"}],"active":"false","m_ok":"0"},{"active":"true","m_ok":"0","children":[{"m_total":"2","active":"false","m_ok":"0","children":[{"name":"Number of downloads on the web site","mnemo":"DL_REPO_1M","ind":null,"type":"metric","active":"false","m_ok":"0","value":null,"m_total":"1"},{"name":"Number of downloads on update site","mnemo":"DL_UPDATE_SITE_1M","type":"metric","ind":null,"value":null,"active":"false","m_ok":"0","m_total":"1"}],"type":"concept","ind":null,"mnemo":"DOWNLOADS","name":"Downloads"},{"mnemo":"INSTALL","name":"Installations","type":"concept","ind":null,"m_ok":"0","active":"true","children":[{"m_total":"1","active":"false","m_ok":"0","value":null,"ind":null,"type":"metric","name":"Installation survey","mnemo":"SURVEY_INSTALL"},{"m_ok":"0","active":"true","value":null,"m_total":"1","mnemo":"MKT_INSTALL_SUCCESS_1M","name":"Number of successfull installs on the Marketplace","ind":null,"type":"metric"}],"m_total":"2"}],"m_total":"4","mnemo":"QM_USAGE","name":"Usage","type":"attribute","ind":null},{"mnemo":"QM_FEEDBACK","name":"User feedback","ind":null,"type":"attribute","active":"true","m_ok":"0","children":[{"m_ok":"0","active":"true","children":[{"m_ok":"0","active":"true","value":null,"m_total":"1","mnemo":"MKT_FAV","name":"Number of favourites on the Marketplace","type":"metric","ind":null}],"m_total":"1","mnemo":"MKT_FEEDBACK","name":"Marketplace feedback","ind":null,"type":"concept"}],"m_total":"1"}],"m_ok":"3","active":"true","m_total":"19","name":"Ecosystem","mnemo":"QM_ECOSYSTEM","ind":1,"type":"attribute"},{"children":[{"children":[{"m_total":"1","children":[{"m_total":"1","active":"true","m_ok":"0","value":null,"type":"metric","ind":null,"name":"SCM information","mnemo":"PUB_SCM_INFO_PMI"}],"m_ok":"0","active":"true","type":"concept","ind":null,"name":"SCM information access","mnemo":"PUB_SCM_INFO"},{"type":"concept","ind":1,"name":"SCM usage","mnemo":"SCM_USAGE","m_total":"2","children":[{"type":"metric","ind":1,"mnemo":"SCM_COMMITS_1M","name":"SCM Commits","m_total":"1","m_ok":"1","active":"true","value":0},{"m_ok":"1","active":"true","value":0,"m_total":"1","name":"SCM committers","mnemo":"SCM_COMMITTERS_1M","type":"metric","ind":1}],"m_ok":"2","active":"true"}],"m_ok":"2","active":"true","m_total":"3","name":"Configuration Management","mnemo":"QM_SCM","ind":1,"type":"attribute"},{"type":"attribute","ind":2,"mnemo":"QM_ITS","name":"Change Management","m_total":"3","m_ok":"2","active":"true","children":[{"ind":null,"type":"concept","name":"ITS information access","mnemo":"PUB_ITS_INFO","m_total":"1","children":[{"m_total":"1","value":null,"active":"true","m_ok":"0","ind":null,"type":"metric","name":"ITS information","mnemo":"PUB_ITS_INFO_PMI"}],"m_ok":"0","active":"true"},{"m_total":"2","active":"true","m_ok":"2","children":[{"m_total":"1","active":"true","m_ok":"1","value":1,"ind":4,"type":"metric","name":"ITS updates","mnemo":"ITS_UPDATES_1M"},{"mnemo":"ITS_AUTH_1M","name":"ITS authors","ind":1,"type":"metric","active":"true","m_ok":"1","value":0,"m_total":"1"}],"type":"concept","ind":2,"mnemo":"ITS_USAGE","name":"ITS usage"}]},{"active":"false","m_ok":"0","children":[{"ind":null,"type":"concept","name":"Licensing","mnemo":"LIC","m_total":"1","children":[{"m_total":"1","m_ok":"0","active":"false","value":null,"type":"metric","ind":null,"mnemo":"LIC_IDENT","name":"License identification"}],"active":"false","m_ok":"0"},{"children":[{"active":"false","value":null,"m_ok":"0","m_total":"1","name":"IP log code coverage","mnemo":"IP_LOG_COV","type":"metric","ind":null}],"m_ok":"0","active":"false","m_total":"1","name":"IP Log","mnemo":"IP_LOG","type":"concept","ind":null}],"m_total":"2","mnemo":"QM_IP","name":"Intellectual Property Management","ind":null,"type":"attribute"},{"m_total":"3","m_ok":"0","active":"true","children":[{"active":"false","m_ok":"0","children":[{"ind":null,"type":"metric","mnemo":"PLAN_NEXT_MILESTONE","name":"Project is on time for next milestone","m_total":"1","active":"false","m_ok":"0","value":null}],"m_total":"1","mnemo":"PLAN_ON_TIME","name":"Plan on time","type":"concept","ind":null},{"active":"true","m_ok":"0","children":[{"type":"metric","ind":null,"name":"Number of milestones","mnemo":"PLAN_MILESTONES_VOL","m_total":"1","active":"true","value":null,"m_ok":"0"},{"ind":null,"type":"metric","name":"Reviews success rate","mnemo":"PLAN_REVIEWS_SUCCESS_RATE","m_total":"1","active":"true","m_ok":"0","value":null}],"m_total":"2","mnemo":"PLAN_RELEASES","name":"Milestones","type":"concept","ind":null}],"type":"attribute","ind":null,"mnemo":"QM_PLAN","name":"Planning Management"},{"type":"attribute","ind":2,"name":"Test Management","mnemo":"QM_TST","m_total":"4","children":[{"m_total":"2","children":[{"m_total":"1","active":"true","m_ok":"1","value":0,"type":"metric","ind":2,"mnemo":"LINE_COVERAGE","name":"Percentage of lines of code covered by tests"},{"mnemo":"BRANCH_COVERAGE","name":"Percentage of branches covered by tests","type":"metric","ind":2,"value":0,"active":"true","m_ok":"1","m_total":"1"}],"active":"true","m_ok":"2","ind":2,"type":"concept","name":"Test coverage","mnemo":"TST_COV"},{"m_total":"1","active":"true","m_ok":"0","children":[{"name":"Number of tests relative to the code size","mnemo":"TST_VOL_IDX","type":"metric","ind":null,"active":"true","value":null,"m_ok":"0","m_total":"1"}],"ind":null,"type":"concept","mnemo":"TST_VOL","name":"Number of tests"},{"name":"Test success density","mnemo":"TST_SUCCESS","ind":null,"type":"concept","children":[{"active":"true","value":null,"m_ok":"0","m_total":"1","mnemo":"TEST_SUCCESS_DENSITY","name":"Test success density","ind":null,"type":"metric"}],"m_ok":"0","active":"true","m_total":"1"}],"m_ok":"2","active":"true"}],"active":"true","m_ok":"6","m_total":"15","name":"Process","mnemo":"QM_PROCESS","type":"attribute","ind":1},{"active":"true","m_ok":"12","children":[{"m_total":"8","children":[{"m_total":"1","active":"true","m_ok":"1","children":[{"type":"metric","ind":5,"mnemo":"NCLOC","name":"Source Lines Of Code","m_total":"1","active":"true","value":17003,"m_ok":"1"}],"type":"concept","ind":5,"mnemo":"CODE_SIZE","name":"Code size"},{"ind":null,"type":"concept","name":"Access points","mnemo":"ALL_DATA","m_total":"2","children":[{"type":"metric","ind":null,"name":"Average number of attributes","mnemo":"ATTRS","m_total":"1","m_ok":"0","active":"false","value":null},{"mnemo":"METHS","name":"Average number of methods","type":"metric","ind":null,"active":"false","m_ok":"0","value":null,"m_total":"1"}],"active":"false","m_ok":"0"},{"children":[{"active":"true","m_ok":"1","value":2.5,"m_total":"1","mnemo":"FUNCTION_COMPLEXITY","name":"Average Cyclomatic Complexity","type":"metric","ind":5},{"name":"Depth of Inheritance Tree","mnemo":"MDIT","ind":null,"type":"metric","m_ok":"0","active":"false","value":null,"m_total":"1"}],"active":"true","m_ok":"1","m_total":"2","name":"Code complexity","mnemo":"CPX","ind":5,"type":"concept"},{"ind":2,"type":"concept","name":"Code documentation","mnemo":"CODE_DOC","m_total":"1","children":[{"type":"metric","ind":2,"name":"Comment rate","mnemo":"COMMENT_LINES_DENSITY","m_total":"1","active":"true","m_ok":"1","value":16.4}],"active":"true","m_ok":"1"},{"type":"concept","ind":null,"mnemo":"PRACTICES_ANA","name":"Analysability practices","m_total":"2","active":"true","m_ok":"0","children":[{"ind":null,"type":"metric","name":"Average number of non-conformities for analysability","mnemo":"NCC_ANA_IDX","m_total":"1","active":"true","value":null,"m_ok":"0"},{"value":null,"active":"true","m_ok":"0","m_total":"1","name":"Adherence to analysability rules","mnemo":"ROKR_ANA","ind":null,"type":"metric"}]}],"m_ok":"3","active":"true","type":"attribute","ind":4,"name":"Analysability","mnemo":"QM_ANA"},{"m_total":"6","active":"true","m_ok":"2","children":[{"ind":5,"type":"concept","mnemo":"PUBLIC_DATA","name":"Public access points","m_total":"1","m_ok":"1","active":"false","children":[{"mnemo":"PUBLIC_API","name":"Public API","ind":5,"type":"metric","value":1292,"active":"false","m_ok":"1","m_total":"1"}]},{"mnemo":"CPX","name":"Code complexity","type":"concept","ind":5,"active":"true","m_ok":"1","children":[{"active":"true","value":2.5,"m_ok":"1","m_total":"1","name":"Average Cyclomatic Complexity","mnemo":"FUNCTION_COMPLEXITY","ind":5,"type":"metric"},{"m_total":"1","active":"false","m_ok":"0","value":null,"type":"metric","ind":null,"mnemo":"MDIT","name":"Depth of Inheritance Tree"}],"m_total":"2"},{"children":[{"m_total":"1","value":null,"active":"true","m_ok":"0","ind":null,"type":"metric","name":"Cloning density","mnemo":"DUPLICATED_LINES_DENSITY"}],"m_ok":"0","active":"true","m_total":"1","name":"Code cloning","mnemo":"CODE_CLONE","ind":null,"type":"concept"},{"active":"true","m_ok":"0","children":[{"type":"metric","ind":null,"mnemo":"NCC_CHA_IDX","name":"Average number of non-conformities for changeability","m_total":"1","m_ok":"0","active":"true","value":null},{"name":"Adherence to changeability rules","mnemo":"ROKR_CHA","ind":null,"type":"metric","m_ok":"0","active":"true","value":null,"m_total":"1"}],"m_total":"2","mnemo":"PRACTICES_CHA","name":"Changeability practices","ind":null,"type":"concept"}],"ind":5,"type":"attribute","mnemo":"QM_CHA","name":"Changeability"},{"ind":4,"type":"attribute","mnemo":"QM_REL","name":"Reliability","m_total":"9","m_ok":"4","active":"true","children":[{"ind":5,"type":"concept","mnemo":"PUBLIC_DATA","name":"Public access points","m_total":"1","active":"false","m_ok":"1","children":[{"type":"metric","ind":5,"mnemo":"PUBLIC_API","name":"Public API","m_total":"1","active":"false","value":1292,"m_ok":"1"}]},{"type":"concept","ind":5,"mnemo":"CPX","name":"Code complexity","m_total":"2","m_ok":"1","active":"true","children":[{"name":"Average Cyclomatic Complexity","mnemo":"FUNCTION_COMPLEXITY","ind":5,"type":"metric","value":2.5,"active":"true","m_ok":"1","m_total":"1"},{"ind":null,"type":"metric","name":"Depth of Inheritance Tree","mnemo":"MDIT","m_total":"1","active":"false","m_ok":"0","value":null}]},{"active":"true","m_ok":"0","children":[{"value":null,"active":"true","m_ok":"0","m_total":"1","mnemo":"SCM_STABILITY_1M","name":"File stability index","type":"metric","ind":null}],"m_total":"1","mnemo":"SCM_STABILITY","name":"SCM Stability","type":"concept","ind":null},{"m_total":"3","m_ok":"2","active":"true","children":[{"mnemo":"ITS_FIX_MED_1M","name":"Median time to fix bug","ind":5,"type":"metric","active":"true","m_ok":"1","value":0,"m_total":"1"},{"name":"Number of open bugs","mnemo":"ITS_BUGS_OPENED_1M","type":"metric","ind":null,"active":"true","value":null,"m_ok":"0","m_total":"1"},{"ind":1,"type":"metric","name":"Defect density","mnemo":"ITS_BUGS_DENSITY","m_total":"1","m_ok":"1","active":"true","value":500}],"ind":3,"type":"concept","mnemo":"ITS_REL","name":"ITS Reliability"},{"ind":null,"type":"concept","mnemo":"PRACTICES_REL","name":"Reliability practices","m_total":"2","m_ok":"0","active":"true","children":[{"mnemo":"NCC_REL_IDX","name":"Average number of non-conformities for reliability","type":"metric","ind":null,"m_ok":"0","active":"true","value":null,"m_total":"1"},{"name":"Adherence to reliability rules","mnemo":"ROKR_REL","ind":null,"type":"metric","active":"true","value":null,"m_ok":"0","m_total":"1"}]}]},{"m_total":"5","children":[{"ind":5,"type":"concept","name":"Public access points","mnemo":"PUBLIC_DATA","m_total":"1","children":[{"name":"Public API","mnemo":"PUBLIC_API","type":"metric","ind":5,"active":"false","value":1292,"m_ok":"1","m_total":"1"}],"active":"false","m_ok":"1"},{"m_total":"1","m_ok":"1","active":"true","children":[{"ind":2,"type":"metric","mnemo":"LINE_COVERAGE","name":"Percentage of lines of code covered by tests","m_total":"1","value":0,"m_ok":"1","active":"true"}],"ind":2,"type":"concept","mnemo":"TST_COV","name":"Test coverage"},{"m_total":"1","children":[{"ind":2,"type":"metric","name":"Comment rate","mnemo":"COMMENT_LINES_DENSITY","m_total":"1","active":"true","m_ok":"1","value":16.4}],"m_ok":"1","active":"true","ind":2,"type":"concept","name":"Code documentation","mnemo":"CODE_DOC"},{"m_total":"2","m_ok":"0","active":"true","children":[{"m_ok":"0","active":"true","value":null,"m_total":"1","name":"Average number of non-conformities for reusability","mnemo":"NCC_REU_IDX","type":"metric","ind":null},{"active":"true","m_ok":"0","value":null,"m_total":"1","name":"Adherence to reusability rules","mnemo":"ROKR_REU","ind":null,"type":"metric"}],"ind":null,"type":"concept","mnemo":"PRACTICES_REU","name":"Reusability practices"}],"active":"true","m_ok":"3","ind":3,"type":"attribute","name":"Reusability","mnemo":"QM_REU"}],"m_total":"28","mnemo":"QM_PRODUCT","name":"Product","type":"attribute","ind":4}],"active":"true","m_ok":"21","m_total":"62","name":"Project Quality","mnemo":"QM_QUALITY","ind":2,"type":"attribute"}]}