{"name":"Metrics for project modeling.emfcompare","version":"Generated by the dashboard - Thu Oct  1 01:19:24 2015","children":{"NCC_REL":"125","NCC_CHA_IDX":"1.14925373134328","RULES_REL":"27","NCC_ANA_IDX":"3.95522388059702","SCM_STABILITY_3M":"1.39","RULES":"61","NCLOC":"134777","MKT_INSTALL_SUCCESS_1M":"50","ROKR":"19.672131147541","SCM_COMMITS_3M":"72","COMMENT_LINES_DENSITY":"27.3","RULES_REU":"4","RKO_REL":"5","SCM_COMMITTED_FILES_3M":"468","MLS_USR_RESP_RATIO_3M":"8","RULES_ANA":"12","SCM_COMMITTERS_3M":"9","MLS_USR_SUBJ_3M":"2","TST_VOL_IDX":"14.0528428441055","MKT_FAV":"14","ITS_BUGS_DENSITY":"4.62","NCC_REL_IDX":"0.932835820895522","ROKR_REL":"81.4814814814815","ROKR_CHA":"50","MLS_DEV_AUTH_3M":"0","MLS_DEV_SUBJ_3M":"0","NCC_REU":"0","RKO_CHA":"4","ITS_UPDATES_3M":"40","MLS_DEV_VOL_3M":"0","COMPLEXITY":"22134","MLS_USR_AUTH_3M":"4","ROK_CHA":"4","RKO_REU":"0","IS_FB_OK":"1","FUNCTIONS":"10754","NCC_CHA":"154","PLAN_MILESTONES_VOL":"36","BRANCH_COVERAGE":"47.8","TEST_SUCCESS_DENSITY":"100","MLS_USR_VOL_3M":"21","UNCOVERED_LINES":"24096","RULES_CHA":"8","TESTS":"1894","ROK_REL":"22","DUPLICATED_LINES":"30210","ROK_ANA":"6","FUNCTION_COMPLEXITY":"2","ITS_AUTH_3M":"8","LINE_COVERAGE":"70.6","NCC_ANA":"530","ROKR_ANA":"50","NCC":"660","IS_PMD_OK":"1","PUBLIC_API":"7937","DUPLICATED_LINES_DENSITY":"12","ROK_REU":"0","PUB_ITS_INFO_PMI":"5","MLS_USR_RESP_TIME_MED_3M":"2.79","PLAN_REVIEWS_SUCCESS_RATE":"60","ITS_BUGS_OPEN":"42","RKO_ANA":"6","PUB_SCM_INFO_PMI":"5","ITS_FIX_MED_3M":"14.69"}}