{"name":"Metrics for project polarsys.capella","version":"Generated by the dashboard - Fri Nov  6 03:28:12 2015","children":{"PUBLIC_API":"18494","NCC_ANA":"4024","DUPLICATED_LINES_DENSITY":"7.4","MLS_USR_RESP_TIME_MED_3M":"0.88","RULES_REL":"27","ROKR_REU":"75","RULES":"61","PUB_ITS_INFO_PMI":"5","SCM_COMMITTERS_3M":"12","MLS_USR_RESP_RATIO_3M":"1.2","ITS_AUTH_3M":"14","ITS_UPDATES_3M":"240","PUB_SCM_INFO_PMI":"5","ROKR":"29.5081967213115","MLS_USR_SUBJ_3M":"46","IS_FB_OK":"1","RULES_CHA":"8","PLAN_MILESTONES_VOL":"3","RKO_REL":"8","FUNCTION_COMPLEXITY":"3.1","SCM_COMMITS_3M":"180","NCC_CHA_IDX":"7.96449704142012","ROK_ANA":"4","NCC_REU":"8","NCLOC":"338255","RKO_ANA":"8","RULES_REU":"4","DUPLICATED_LINES":"42399","COMPLEXITY":"79669","MLS_USR_VOL_3M":"74","ROKR_REL":"70.3703703703704","ROK_REU":"3","SCM_STABILITY_3M":"1.7","SCM_COMMITTED_FILES_3M":"4521","ITS_FIX_MED_3M":"3.12","ROKR_CHA":"37.5","ITS_BUGS_OPEN":"139","RKO_CHA":"5","MLS_DEV_VOL_3M":"0","NCC_CHA":"2692","PLAN_REVIEWS_SUCCESS_RATE":"66.6666666666667","RULES_ANA":"12","ROK_CHA":"3","MLS_USR_AUTH_3M":"27","MLS_DEV_AUTH_3M":"0","NCC_REL":"2207","NCC_REU_IDX":"0.0236686390532544","MLS_DEV_SUBJ_3M":"0","NCC":"6430","IS_PMD_OK":"1","ITS_BUGS_DENSITY":"0.92","RKO_REU":"1","NCC_REL_IDX":"6.52958579881657","COMMENT_LINES_DENSITY":"15","FUNCTIONS":"25467","ROK_REL":"19","ROKR_ANA":"33.3333333333333","NCC_ANA_IDX":"11.905325443787"}}