{"version":"1.0.1","children":[{"mnemo":"QM_QUALITY","active":"true","name":"Project Quality","children":[{"name":"Ecosystem","mnemo":"QM_ECOSYSTEM","active":"true","type":"attribute","value":null,"children":[{"children":[{"name":"Developer ML activity","active":"true","mnemo":"MLS_DEV_ACTIVITY","value":null,"type":"concept","children":[{"active":"true","mnemo":"MLS_DEV_VOL_1M","name":"Developer ML posts","value":"0","type":"metric"}]},{"active":"true","mnemo":"MLS_USR_ACTIVITY","name":"User ML activity","children":[{"active":"true","mnemo":"MLS_USR_VOL_1M","name":"User ML posts","value":null,"type":"metric"}],"value":null,"type":"concept"},{"value":null,"type":"concept","children":[{"active":"true","mnemo":"SCM_COMMITS_1M","name":"SCM Commits","value":"126","type":"metric"},{"name":"Files committed","mnemo":"SCM_COMMITTED_FILES_1M","active":"true","type":"metric","value":"2268"}],"name":"SCM activity","active":"true","mnemo":"SCM_ACTIVITY"}],"type":"attribute","value":null,"mnemo":"QM_ACTIVITY","active":"true","name":"Activity"},{"value":null,"type":"attribute","children":[{"name":"Developer ML activity","mnemo":"MLS_DEV_ACTIVITY","active":"true","type":"concept","value":null,"children":[{"mnemo":"MLS_DEV_AUTH_1M","active":"true","name":"Developer ML authors","type":"metric","value":null}]},{"name":"User ML diversity","mnemo":"MLS_USR_DIVERSITY","active":"true","type":"concept","value":null,"children":[{"value":null,"type":"metric","active":"true","mnemo":"MLS_USR_AUTH_1M","name":"User ML authors"}]},{"name":"SCM diversity","mnemo":"SCM_DIVERSITY","active":"true","type":"concept","value":null,"children":[{"type":"metric","value":"9","mnemo":"SCM_COMMITTERS_1M","active":"true","name":"SCM committers"}]}],"name":"Diversity","active":"true","mnemo":"QM_DIVERSITY"},{"name":"Responsiveness","mnemo":"QM_RESPONSIVENESS","active":"true","type":"attribute","value":null,"children":[{"active":"true","mnemo":"MLS_DEV_RESPONSIVENESS","name":"Developer ML responsiveness","children":[{"type":"metric","value":null,"mnemo":"MLS_DEV_RESP_TIME_MED_1M","active":"true","name":"Developer ML response time"}],"value":null,"type":"concept"},{"children":[{"name":"User ML response time","active":"true","mnemo":"MLS_USR_RESP_TIME_MED_1M","value":"0","type":"metric"}],"type":"concept","value":null,"mnemo":"MLS_USR_RESPONSIVENESS","active":"true","name":"User ML responsiveness"}]},{"children":[{"value":null,"type":"concept","children":[{"value":"0","type":"metric","active":"true","mnemo":"MLS_DEV_RESP_RATIO_1M","name":"Developer ML response ratio"},{"name":"Developer ML subjects","active":"true","mnemo":"MLS_DEV_SUBJ_1M","value":"0","type":"metric"}],"name":"Developer ML support","active":"true","mnemo":"MLS_DEV_SUPPORT"},{"name":"User ML support","active":"true","mnemo":"MLS_USR_SUPPORT","value":null,"type":"concept","children":[{"name":"User ML response ratio","active":"true","mnemo":"MLS_USR_RESP_RATIO_1M","value":null,"type":"metric"},{"type":"metric","value":null,"name":"User ML subjects","mnemo":"MLS_USR_SUBJ_1M","active":"true"}]}],"value":null,"type":"attribute","active":"true","mnemo":"QM_SUPPORT","name":"Support"},{"active":"false","mnemo":"QM_VISIBILITY","name":"Visibility","children":[{"name":"Visibility in research","mnemo":"PUB_CONF","active":"false","type":"concept","value":null,"children":[{"mnemo":"PUB_CONF_VOL","active":"false","name":"Number of publications","type":"metric","value":null}]}],"value":null,"type":"attribute"},{"children":[{"active":"false","mnemo":"DOWNLOADS","name":"Downloads","children":[{"value":"0","type":"metric","name":"Number of downloads on the web site","active":"false","mnemo":"DL_REPO_1M"},{"active":"false","mnemo":"DL_UPDATE_SITE_1M","name":"Number of downloads on update site","value":"0","type":"metric"}],"value":null,"type":"concept"},{"value":null,"type":"concept","children":[{"type":"metric","value":null,"mnemo":"SURVEY_INSTALL","active":"false","name":"Installation survey"},{"value":"357","type":"metric","name":"Number of successfull installs on the Marketplace","active":"true","mnemo":"MKT_INSTALL_SUCCESS_1M"}],"name":"Installations","active":"true","mnemo":"INSTALL"}],"type":"attribute","value":null,"mnemo":"QM_USAGE","active":"true","name":"Usage"},{"children":[{"type":"concept","value":null,"children":[{"name":"Number of favourites on the Marketplace","mnemo":"MKT_FAV","active":"true","type":"metric","value":"0"}],"name":"Marketplace feedback","mnemo":"MKT_FEEDBACK","active":"true"}],"type":"attribute","value":null,"mnemo":"QM_FEEDBACK","active":"true","name":"User feedback"}]},{"children":[{"name":"Configuration Management","mnemo":"QM_SCM","active":"true","type":"attribute","value":null,"children":[{"name":"SCM information access","active":"true","mnemo":"PUB_SCM_INFO","value":null,"type":"concept","children":[{"type":"metric","value":"5","mnemo":"PUB_SCM_INFO_PMI","active":"true","name":"SCM information"}]},{"type":"concept","value":null,"children":[{"type":"metric","value":"126","mnemo":"SCM_COMMITS_1M","active":"true","name":"SCM Commits"},{"type":"metric","value":"9","name":"SCM committers","mnemo":"SCM_COMMITTERS_1M","active":"true"}],"name":"SCM usage","mnemo":"SCM_USAGE","active":"true"}]},{"name":"Change Management","active":"true","mnemo":"QM_ITS","value":null,"type":"attribute","children":[{"children":[{"type":"metric","value":"5","name":"ITS information","mnemo":"PUB_ITS_INFO_PMI","active":"true"}],"type":"concept","value":null,"mnemo":"PUB_ITS_INFO","active":"true","name":"ITS information access"},{"children":[{"active":"true","mnemo":"ITS_UPDATES_1M","name":"ITS updates","value":"192","type":"metric"},{"active":"true","mnemo":"ITS_AUTH_1M","name":"ITS authors","value":"19","type":"metric"}],"type":"concept","value":null,"mnemo":"ITS_USAGE","active":"true","name":"ITS usage"}]},{"value":null,"type":"attribute","children":[{"active":"false","mnemo":"LIC","name":"Licensing","children":[{"name":"License identification","mnemo":"LIC_IDENT","active":"false","type":"metric","value":null}],"value":null,"type":"concept"},{"children":[{"value":null,"type":"metric","active":"false","mnemo":"IP_LOG_COV","name":"IP log code coverage"}],"type":"concept","value":null,"mnemo":"IP_LOG","active":"false","name":"IP Log"}],"name":"Intellectual Property Management","active":"false","mnemo":"QM_IP"},{"type":"attribute","value":null,"children":[{"children":[{"value":null,"type":"metric","name":"Project is on time for next milestone","active":"false","mnemo":"PLAN_NEXT_MILESTONE"}],"type":"concept","value":null,"mnemo":"PLAN_ON_TIME","active":"false","name":"Plan on time"},{"mnemo":"PLAN_RELEASES","active":"true","name":"Milestones","children":[{"active":"true","mnemo":"PLAN_MILESTONES_VOL","name":"Number of milestones","value":"0","type":"metric"},{"active":"true","mnemo":"PLAN_REVIEWS_SUCCESS_RATE","name":"Milestone success rate","value":"0","type":"metric"}],"type":"concept","value":null}],"name":"Planning Management","mnemo":"QM_PLAN","active":"true"},{"type":"attribute","value":null,"children":[{"name":"Test coverage","active":"true","mnemo":"TST_COV","value":null,"type":"concept","children":[{"type":"metric","value":null,"name":"Percentage of lines of code covered by tests","mnemo":"TST_COV_LINES","active":"true"},{"value":null,"type":"metric","name":"Percentage of branches covered by tests","active":"true","mnemo":"TST_COV_BRANCHES"}]},{"name":"Number of tests","active":"true","mnemo":"TST_VOL","value":null,"type":"concept","children":[{"value":null,"type":"metric","active":"true","mnemo":"TST_VOL_IDX","name":"Number of tests relative to the code size"}]},{"active":"true","mnemo":"TST_SUCCESS","name":"Test success density","children":[{"mnemo":"TST_SUCCESS_LAST","active":"true","name":"Test success density","type":"metric","value":null}],"value":null,"type":"concept"}],"name":"Test Management","mnemo":"QM_TST","active":"true"}],"type":"attribute","value":null,"mnemo":"QM_PROCESS","active":"true","name":"Process"},{"active":"true","mnemo":"QM_PRODUCT","name":"Product","children":[{"mnemo":"QM_ANA","active":"true","name":"Analysability","children":[{"children":[{"value":null,"type":"metric","active":"true","mnemo":"SLOC","name":"Source Lines Of Code"}],"value":null,"type":"concept","active":"true","mnemo":"CODE_SIZE","name":"Code size"},{"type":"concept","value":null,"children":[{"value":null,"type":"metric","name":"Average number of attributes","active":"false","mnemo":"ATTRS"},{"mnemo":"METHS","active":"false","name":"Average number of methods","type":"metric","value":null}],"name":"Access points","mnemo":"ALL_DATA","active":"false"},{"name":"Code complexity","active":"true","mnemo":"CPX","value":null,"type":"concept","children":[{"value":null,"type":"metric","active":"true","mnemo":"VG","name":"Average Cyclomatic Complexity"},{"type":"metric","value":null,"mnemo":"MDIT","active":"false","name":"Depth of Inheritance Tree"}]},{"value":null,"type":"concept","children":[{"value":null,"type":"metric","active":"true","mnemo":"COMR","name":"Comment rate"}],"name":"Code documentation","active":"true","mnemo":"CODE_DOC"},{"value":null,"type":"concept","children":[{"type":"metric","value":null,"mnemo":"NCC_ANA_IDX","active":"true","name":"Average number of non-conformities for analysability"},{"value":"47.6190476190476","type":"metric","active":"true","mnemo":"ROKR_ANA","name":"Adherence to analysability rules"}],"name":"Analysability practices","active":"true","mnemo":"PRACTICES_ANA"}],"type":"attribute","value":null},{"value":null,"type":"attribute","children":[{"value":null,"type":"concept","children":[{"value":null,"type":"metric","active":"false","mnemo":"ATTRS_PUBLIC","name":"Average number of public attributes"},{"active":"false","mnemo":"METHS_PUBLIC","name":"Average number of public methods","value":null,"type":"metric"}],"name":"Public access points","active":"false","mnemo":"PUBLIC_DATA"},{"name":"Code complexity","mnemo":"CPX","active":"true","type":"concept","value":null,"children":[{"value":null,"type":"metric","active":"true","mnemo":"VG","name":"Average Cyclomatic Complexity"},{"active":"false","mnemo":"MDIT","name":"Depth of Inheritance Tree","value":null,"type":"metric"}]},{"children":[{"name":"Cloning density","mnemo":"CLONE_IDX","active":"true","type":"metric","value":null}],"value":null,"type":"concept","active":"true","mnemo":"CODE_CLONE","name":"Code cloning"},{"mnemo":"PRACTICES_CHA","active":"true","name":"Changeability practices","children":[{"name":"Average number of non-conformities for changeability","active":"true","mnemo":"NCC_CHA_IDX","value":null,"type":"metric"},{"type":"metric","value":"47.3684210526316","name":"Adherence to changeability rules","mnemo":"ROKR_CHA","active":"true"}],"type":"concept","value":null}],"name":"Changeability","active":"true","mnemo":"QM_CHA"},{"mnemo":"QM_REL","active":"true","name":"Reliability","children":[{"mnemo":"PUBLIC_DATA","active":"false","name":"Public access points","children":[{"type":"metric","value":null,"name":"Average number of public attributes","mnemo":"ATTRS_PUBLIC","active":"false"},{"active":"false","mnemo":"METHS_PUBLIC","name":"Average number of public methods","value":null,"type":"metric"}],"type":"concept","value":null},{"children":[{"mnemo":"VG","active":"true","name":"Average Cyclomatic Complexity","type":"metric","value":null},{"type":"metric","value":null,"name":"Depth of Inheritance Tree","mnemo":"MDIT","active":"false"}],"value":null,"type":"concept","active":"true","mnemo":"CPX","name":"Code complexity"},{"name":"SCM Stability","mnemo":"SCM_STABILITY","active":"true","type":"concept","value":null,"children":[{"active":"true","mnemo":"SCM_STABILITY_1M","name":"File stability index","value":null,"type":"metric"}]},{"value":null,"type":"concept","children":[{"name":"Median time to fix bug","active":"true","mnemo":"ITS_FIX_MED_1M","value":"18.16","type":"metric"},{"mnemo":"ITS_BUGS_OPEN","active":"true","name":"Number of open bugs","type":"metric","value":null},{"type":"metric","value":"0.1","mnemo":"ITS_BUGS_DENSITY","active":"true","name":"Defect density"}],"name":"ITS Reliability","active":"true","mnemo":"ITS_REL"},{"name":"Reliability practices","mnemo":"PRACTICES_REL","active":"true","type":"concept","value":null,"children":[{"name":"Average number of non-conformities for reliability","mnemo":"NCC_REL_IDX","active":"true","type":"metric","value":null},{"type":"metric","value":"72.3404255319149","name":"Adherence to reliability rules","mnemo":"ROKR_REL","active":"true"}]}],"type":"attribute","value":null},{"value":null,"type":"attribute","children":[{"mnemo":"PUBLIC_DATA","active":"false","name":"Public access points","children":[{"name":"Average number of public attributes","active":"false","mnemo":"ATTRS_PUBLIC","value":null,"type":"metric"},{"mnemo":"METHS_PUBLIC","active":"false","name":"Average number of public methods","type":"metric","value":null}],"type":"concept","value":null},{"active":"true","mnemo":"TST_COV","name":"Test coverage","children":[{"name":"Percentage of lines of code covered by tests","active":"true","mnemo":"TST_COV_LINES","value":null,"type":"metric"}],"value":null,"type":"concept"},{"name":"Code documentation","mnemo":"CODE_DOC","active":"true","type":"concept","value":null,"children":[{"type":"metric","value":null,"mnemo":"COMR","active":"true","name":"Comment rate"}]},{"value":null,"type":"concept","children":[{"name":"Average number of non-conformities for reusability","mnemo":"NCC_REU_IDX","active":"true","type":"metric","value":null},{"value":"55.5555555555556","type":"metric","name":"Adherence to reusability rules","active":"true","mnemo":"ROKR_REU"}],"name":"Reusability practices","active":"true","mnemo":"PRACTICES_REU"}],"name":"Reusability","active":"true","mnemo":"QM_REU"}],"value":null,"type":"attribute"}],"type":"attribute","value":null}],"name":"PolarSys Quality Model"}