{"version":"1.0.1","children":[{"type":"attribute","children":[{"value":null,"active":"true","children":[{"value":null,"type":"attribute","children":[{"value":null,"children":[{"value":"0","type":"metric","active":"true","mnemo":"MLS_DEV_VOL_1M","name":"Developer ML posts"}],"type":"concept","active":"true","name":"Developer ML activity","mnemo":"MLS_DEV_ACTIVITY"},{"active":"true","children":[{"name":"User ML posts","mnemo":"MLS_USR_VOL_1M","active":"true","type":"metric","value":null}],"type":"concept","value":null,"mnemo":"MLS_USR_ACTIVITY","name":"User ML activity"},{"name":"SCM activity","mnemo":"SCM_ACTIVITY","type":"concept","children":[{"type":"metric","active":"true","value":"126","name":"SCM Commits","mnemo":"SCM_COMMITS_1M"},{"mnemo":"SCM_COMMITTED_FILES_1M","name":"Files committed","type":"metric","active":"true","value":"2268"}],"active":"true","value":null}],"active":"true","mnemo":"QM_ACTIVITY","name":"Activity"},{"children":[{"mnemo":"MLS_DEV_ACTIVITY","name":"Developer ML activity","value":null,"active":"true","children":[{"mnemo":"MLS_DEV_AUTH_1M","name":"Developer ML authors","value":null,"active":"true","type":"metric"}],"type":"concept"},{"mnemo":"MLS_USR_DIVERSITY","name":"User ML diversity","value":null,"children":[{"type":"metric","active":"true","value":null,"mnemo":"MLS_USR_AUTH_1M","name":"User ML authors"}],"active":"true","type":"concept"},{"mnemo":"SCM_DIVERSITY","name":"SCM diversity","value":null,"type":"concept","children":[{"name":"SCM committers","mnemo":"SCM_COMMITTERS_1M","type":"metric","active":"true","value":"9"}],"active":"true"}],"type":"attribute","active":"true","value":null,"mnemo":"QM_DIVERSITY","name":"Diversity"},{"name":"Responsiveness","mnemo":"QM_RESPONSIVENESS","value":null,"active":"true","children":[{"value":null,"active":"true","children":[{"value":null,"type":"metric","active":"true","name":"Developer ML response time","mnemo":"MLS_DEV_RESP_TIME_MED_1M"}],"type":"concept","mnemo":"MLS_DEV_RESPONSIVENESS","name":"Developer ML responsiveness"},{"value":null,"active":"true","children":[{"name":"User ML response time","mnemo":"MLS_USR_RESP_TIME_MED_1M","value":"0","active":"true","type":"metric"}],"type":"concept","mnemo":"MLS_USR_RESPONSIVENESS","name":"User ML responsiveness"}],"type":"attribute"},{"value":null,"type":"attribute","children":[{"mnemo":"MLS_DEV_SUPPORT","name":"Developer ML support","type":"concept","children":[{"mnemo":"MLS_DEV_RESP_RATIO_1M","name":"Developer ML response ratio","active":"true","type":"metric","value":"0"},{"name":"Developer ML subjects","mnemo":"MLS_DEV_SUBJ_1M","type":"metric","active":"true","value":"0"}],"active":"true","value":null},{"value":null,"active":"true","children":[{"name":"User ML response ratio","mnemo":"MLS_USR_RESP_RATIO_1M","value":null,"type":"metric","active":"true"},{"mnemo":"MLS_USR_SUBJ_1M","name":"User ML subjects","type":"metric","active":"true","value":null}],"type":"concept","name":"User ML support","mnemo":"MLS_USR_SUPPORT"}],"active":"true","mnemo":"QM_SUPPORT","name":"Support"},{"mnemo":"QM_VISIBILITY","name":"Visibility","active":"false","children":[{"children":[{"value":null,"active":"false","type":"metric","name":"Number of publications","mnemo":"PUB_CONF_VOL"}],"type":"concept","active":"false","value":null,"name":"Visibility in research","mnemo":"PUB_CONF"}],"type":"attribute","value":null},{"value":null,"type":"attribute","children":[{"mnemo":"DOWNLOADS","name":"Downloads","type":"concept","children":[{"mnemo":"DL_REPO_1M","name":"Number of downloads on the web site","active":"false","type":"metric","value":"0"},{"mnemo":"DL_UPDATE_SITE_1M","name":"Number of downloads on update site","active":"false","type":"metric","value":"0"}],"active":"false","value":null},{"name":"Installations","mnemo":"INSTALL","children":[{"value":null,"type":"metric","active":"false","mnemo":"SURVEY_INSTALL","name":"Installation survey"},{"mnemo":"MKT_INSTALL_SUCCESS_1M","name":"Number of successfull installs on the Marketplace","value":"357","active":"true","type":"metric"}],"active":"true","type":"concept","value":null}],"active":"true","mnemo":"QM_USAGE","name":"Usage"},{"name":"User feedback","mnemo":"QM_FEEDBACK","type":"attribute","children":[{"type":"concept","children":[{"active":"true","type":"metric","value":"0","mnemo":"MKT_FAV","name":"Number of favourites on the Marketplace"}],"active":"true","value":null,"mnemo":"MKT_FEEDBACK","name":"Marketplace feedback"}],"active":"true","value":null}],"type":"attribute","mnemo":"QM_ECOSYSTEM","name":"Ecosystem"},{"mnemo":"QM_PROCESS","name":"Process","value":null,"type":"attribute","children":[{"value":null,"type":"attribute","children":[{"active":"true","children":[{"mnemo":"PUB_SCM_INFO_PMI","name":"SCM information","type":"metric","active":"true","value":"5"}],"type":"concept","value":null,"name":"SCM information access","mnemo":"PUB_SCM_INFO"},{"name":"SCM usage","mnemo":"SCM_USAGE","active":"true","children":[{"active":"true","type":"metric","value":"126","name":"SCM Commits","mnemo":"SCM_COMMITS_1M"},{"active":"true","type":"metric","value":"9","mnemo":"SCM_COMMITTERS_1M","name":"SCM committers"}],"type":"concept","value":null}],"active":"true","mnemo":"QM_SCM","name":"Configuration Management"},{"mnemo":"QM_ITS","name":"Change Management","value":null,"children":[{"value":null,"type":"concept","children":[{"value":"5","type":"metric","active":"true","name":"ITS information","mnemo":"PUB_ITS_INFO_PMI"}],"active":"true","mnemo":"PUB_ITS_INFO","name":"ITS information access"},{"type":"concept","children":[{"mnemo":"ITS_UPDATES_1M","name":"ITS updates","value":"192","active":"true","type":"metric"},{"name":"ITS authors","mnemo":"ITS_AUTH_1M","active":"true","type":"metric","value":"19"}],"active":"true","value":null,"name":"ITS usage","mnemo":"ITS_USAGE"}],"type":"attribute","active":"true"},{"mnemo":"QM_IP","name":"Intellectual Property Management","value":null,"children":[{"value":null,"active":"false","children":[{"name":"License identification","mnemo":"LIC_IDENT","value":null,"type":"metric","active":"false"}],"type":"concept","name":"Licensing","mnemo":"LIC"},{"value":null,"children":[{"active":"false","type":"metric","value":null,"mnemo":"IP_LOG_COV","name":"IP log code coverage"}],"type":"concept","active":"false","mnemo":"IP_LOG","name":"IP Log"}],"type":"attribute","active":"false"},{"children":[{"name":"Plan on time","mnemo":"PLAN_ON_TIME","value":null,"children":[{"mnemo":"PLAN_NEXT_MILESTONE","name":"Project is on time for next milestone","active":"false","type":"metric","value":null}],"type":"concept","active":"false"},{"mnemo":"PLAN_RELEASES","name":"Milestones","type":"concept","children":[{"type":"metric","active":"true","value":null,"mnemo":"PLAN_MILESTONES_VOL_1Y","name":"Number of milestones"},{"value":"0","type":"metric","active":"true","mnemo":"PLAN_REVIEWS_SUCCESS_RATE","name":"Milestone success rate"}],"active":"true","value":null}],"type":"attribute","active":"true","value":null,"mnemo":"QM_PLAN","name":"Planning Management"},{"mnemo":"QM_TST","name":"Test Management","value":null,"type":"attribute","children":[{"type":"concept","children":[{"mnemo":"TST_COV_LINES","name":"Percentage of lines of code covered by tests","value":null,"active":"true","type":"metric"},{"value":null,"type":"metric","active":"true","mnemo":"TST_COV_BRANCHES","name":"Percentage of branches covered by tests"}],"active":"true","value":null,"name":"Test coverage","mnemo":"TST_COV"},{"value":null,"children":[{"type":"metric","active":"true","value":null,"name":"Number of tests relative to the code size","mnemo":"TST_VOL_IDX"}],"type":"concept","active":"true","name":"Number of tests","mnemo":"TST_VOL"},{"children":[{"mnemo":"TST_SUCCESS_LAST","name":"Test success density","active":"true","type":"metric","value":null}],"type":"concept","active":"true","value":null,"name":"Test success density","mnemo":"TST_SUCCESS"}],"active":"true"}],"active":"true"},{"mnemo":"QM_PRODUCT","name":"Product","type":"attribute","children":[{"value":null,"children":[{"value":null,"children":[{"mnemo":"SLOC","name":"Source Lines Of Code","type":"metric","active":"true","value":null}],"active":"true","type":"concept","mnemo":"CODE_SIZE","name":"Code size"},{"type":"concept","children":[{"mnemo":"ATTRS","name":"Average number of attributes","active":"false","type":"metric","value":null},{"name":"Average number of methods","mnemo":"METHS","value":null,"active":"false","type":"metric"}],"active":"false","value":null,"mnemo":"ALL_DATA","name":"Access points"},{"type":"concept","children":[{"mnemo":"VG","name":"Average Cyclomatic Complexity","value":null,"type":"metric","active":"true"},{"name":"Depth of Inheritance Tree","mnemo":"MDIT","value":null,"active":"false","type":"metric"}],"active":"true","value":null,"name":"Code complexity","mnemo":"CPX"},{"type":"concept","children":[{"name":"Comment rate","mnemo":"COMR","value":null,"type":"metric","active":"true"}],"active":"true","value":null,"mnemo":"CODE_DOC","name":"Code documentation"},{"mnemo":"PRACTICES_ANA","name":"Analysability practices","value":null,"type":"concept","children":[{"mnemo":"NCC_ANA_IDX","name":"Average number of non-conformities for analysability","value":null,"active":"true","type":"metric"},{"mnemo":"ROKR_ANA","name":"Adherence to analysability rules","type":"metric","active":"true","value":"47.6190476190476"}],"active":"true"}],"active":"true","type":"attribute","mnemo":"QM_ANA","name":"Analysability"},{"name":"Changeability","mnemo":"QM_CHA","active":"true","children":[{"active":"false","children":[{"name":"Average number of public attributes","mnemo":"ATTRS_PUBLIC","type":"metric","active":"false","value":null},{"mnemo":"METHS_PUBLIC","name":"Average number of public methods","type":"metric","active":"false","value":null}],"type":"concept","value":null,"name":"Public access points","mnemo":"PUBLIC_DATA"},{"mnemo":"CPX","name":"Code complexity","type":"concept","children":[{"value":null,"type":"metric","active":"true","name":"Average Cyclomatic Complexity","mnemo":"VG"},{"name":"Depth of Inheritance Tree","mnemo":"MDIT","type":"metric","active":"false","value":null}],"active":"true","value":null},{"value":null,"active":"true","children":[{"mnemo":"CLONE_IDX","name":"Cloning density","value":null,"active":"true","type":"metric"}],"type":"concept","mnemo":"CODE_CLONE","name":"Code cloning"},{"value":null,"active":"true","children":[{"mnemo":"NCC_CHA_IDX","name":"Average number of non-conformities for changeability","type":"metric","active":"true","value":null},{"name":"Adherence to changeability rules","mnemo":"ROKR_CHA","type":"metric","active":"true","value":"47.3684210526316"}],"type":"concept","mnemo":"PRACTICES_CHA","name":"Changeability practices"}],"type":"attribute","value":null},{"value":null,"type":"attribute","children":[{"active":"false","children":[{"active":"false","type":"metric","value":null,"name":"Average number of public attributes","mnemo":"ATTRS_PUBLIC"},{"active":"false","type":"metric","value":null,"mnemo":"METHS_PUBLIC","name":"Average number of public methods"}],"type":"concept","value":null,"mnemo":"PUBLIC_DATA","name":"Public access points"},{"mnemo":"CPX","name":"Code complexity","value":null,"type":"concept","children":[{"active":"true","type":"metric","value":null,"mnemo":"VG","name":"Average Cyclomatic Complexity"},{"value":null,"active":"false","type":"metric","mnemo":"MDIT","name":"Depth of Inheritance Tree"}],"active":"true"},{"name":"SCM Stability","mnemo":"SCM_STABILITY","type":"concept","children":[{"mnemo":"SCM_STABILITY_1M","name":"File stability index","type":"metric","active":"true","value":null}],"active":"true","value":null},{"active":"true","children":[{"name":"Median time to fix bug","mnemo":"ITS_FIX_MED_1M","type":"metric","active":"true","value":"18.16"},{"value":null,"type":"metric","active":"true","mnemo":"ITS_BUGS_OPEN","name":"Number of open bugs"},{"mnemo":"ITS_BUGS_DENSITY","name":"Defect density","value":"0.1","active":"true","type":"metric"}],"type":"concept","value":null,"name":"ITS Reliability","mnemo":"ITS_REL"},{"mnemo":"PRACTICES_REL","name":"Reliability practices","value":null,"children":[{"name":"Average number of non-conformities for reliability","mnemo":"NCC_REL_IDX","value":null,"type":"metric","active":"true"},{"name":"Adherence to reliability rules","mnemo":"ROKR_REL","type":"metric","active":"true","value":"72.3404255319149"}],"type":"concept","active":"true"}],"active":"true","mnemo":"QM_REL","name":"Reliability"},{"mnemo":"QM_REU","name":"Reusability","children":[{"active":"false","children":[{"value":null,"type":"metric","active":"false","mnemo":"ATTRS_PUBLIC","name":"Average number of public attributes"},{"type":"metric","active":"false","value":null,"name":"Average number of public methods","mnemo":"METHS_PUBLIC"}],"type":"concept","value":null,"name":"Public access points","mnemo":"PUBLIC_DATA"},{"name":"Test coverage","mnemo":"TST_COV","value":null,"active":"true","children":[{"mnemo":"TST_COV_LINES","name":"Percentage of lines of code covered by tests","value":null,"active":"true","type":"metric"}],"type":"concept"},{"children":[{"mnemo":"COMR","name":"Comment rate","value":null,"type":"metric","active":"true"}],"active":"true","type":"concept","value":null,"mnemo":"CODE_DOC","name":"Code documentation"},{"value":null,"active":"true","children":[{"type":"metric","active":"true","value":null,"mnemo":"NCC_REU_IDX","name":"Average number of non-conformities for reusability"},{"value":"55.5555555555556","type":"metric","active":"true","mnemo":"ROKR_REU","name":"Adherence to reusability rules"}],"type":"concept","name":"Reusability practices","mnemo":"PRACTICES_REU"}],"active":"true","type":"attribute","value":null}],"active":"true","value":null}],"active":"true","value":null,"mnemo":"QM_QUALITY","name":"Project Quality"}],"name":"PolarSys Quality Model"}