{"name":"Metrics for project tools.tracecompass","children":{"SCM_COMMITTERS_3M":"10","MLS_USR_RESP_RATIO_3M":"1","RKO_ANA":"7","MLS_USR_VOL_3M":"2","RULES_REU":"4","ROKR_REU":"75","MLS_DEV_VOL_3M":"144","MLS_DEV_SUBJ_3M":"37","PLAN_MILESTONES_VOL":"0","NCC_CHA":"243","MLS_USR_SUBJ_3M":"1","NCLOC":"122513","MLS_DEV_AUTH_3M":"14","UNCOVERED_LINES":"30064","LINE_COVERAGE":"56.2","COMMENT_LINES_DENSITY":"25.6","ITS_AUTH_3M":"11","ITS_BUGS_DENSITY":"1.8","ROK_REU":"3","SCM_COMMITTED_FILES_3M":"839","RULES_CHA":"8","RULES_ANA":"12","NCC_ANA":"687","NCC_CHA_IDX":"1.99180327868852","NCC_REL_IDX":"0.540983606557377","MLS_USR_AUTH_3M":"1","ITS_FIX_MED_3M":"4.86","MLS_DEV_RESP_TIME_MED_3M":"0.25","ROKR":"19.672131147541","MLS_DEV_RESP_RATIO_3M":"2.92","RKO_REU":"1","PUB_ITS_INFO_PMI":"5","FUNCTIONS":"9081","ROK_REL":"23","ROKR_CHA":"50","NCC_ANA_IDX":"5.63114754098361","SCM_STABILITY_3M":"1.36","ROKR_ANA":"41.6666666666667","ITS_BUGS_OPEN":"143","DUPLICATED_LINES_DENSITY":"2.7","NCC_REU":"7","BRANCH_COVERAGE":"45","SCM_COMMITS_3M":"251","RKO_REL":"4","IS_PMD_OK":"1","RKO_CHA":"4","RULES":"61","ROK_CHA":"4","FUNCTION_COMPLEXITY":"3.1","NCC_REU_IDX":"0.0573770491803279","IS_FB_OK":"1","NCC_REL":"66","ROK_ANA":"5","DUPLICATED_LINES":"6104","PLAN_REVIEWS_SUCCESS_RATE":"40","COMPLEXITY":"28178","RULES_REL":"27","PUBLIC_API":"5223","NCC":"760","ROKR_REL":"85.1851851851852","PUB_SCM_INFO_PMI":"5","ITS_UPDATES_3M":"107"},"version":"Generated by the dashboard - Mon Sep 14 04:46:28 2015"}