{"name":"Metrics for project tools.cdt","children":{"TEST_SUCCESS_DENSITY":"100","NCC_REL":"2224","NCC_REL_IDX":"2.38882921589689","ITS_FIX_MED_3M":"11.22","ITS_UPDATES_3M":"371","MLS_USR_VOL_3M":"328","NCC_ANA_IDX":"7.03866809881847","ROKR_REU":"25","DUPLICATED_LINES_DENSITY":"8.1","RKO_REL":"11","PUBLIC_API":"43091","IS_FB_OK":"1","DUPLICATED_LINES":"117190","NCC_CHA":"4440","ROKR":"44.2622950819672","MLS_DEV_RESP_RATIO_3M":"1.67","NCLOC":"931091","RULES_REL":"27","MLS_USR_SUBJ_3M":"11","ITS_BUGS_DENSITY":"18.26","MLS_USR_RESP_TIME_MED_3M":"0.69","RULES_REU":"4","RKO_ANA":"10","NCC_REU":"84","MKT_FAV":"13","ROKR_REL":"59.2592592592593","ROK_REU":"1","MLS_DEV_VOL_3M":"269","RKO_REU":"3","MLS_DEV_AUTH_3M":"45","PUB_ITS_INFO_PMI":"5","NCC_ANA":"6553","SCM_COMMITTERS_3M":"22","RKO_CHA":"7","RULES_ANA":"12","MKT_INSTALL_SUCCESS_1M":"2352","IS_PMD_OK":"1","COMPLEXITY":"229927","MLS_DEV_RESP_TIME_MED_3M":"0.1","PUB_SCM_INFO_PMI":"5","TESTS":"721","MLS_DEV_SUBJ_3M":"101","BRANCH_COVERAGE":"34.8","ROKR_CHA":"12.5","MLS_USR_RESP_RATIO_3M":"16.27","TST_VOL_IDX":"0.774360400863074","FUNCTIONS":"73712","SCM_COMMITTED_FILES_3M":"523","MLS_USR_AUTH_3M":"44","SCM_STABILITY_3M":"1.58","RULES":"61","NCC":"10805","PLAN_MILESTONES_VOL":"0","LINE_COVERAGE":"36.4","RULES_CHA":"8","ITS_BUGS_OPEN":"4502","UNCOVERED_LINES":"334708","ROK_ANA":"2","NCC_CHA_IDX":"4.76906552094522","PLAN_REVIEWS_SUCCESS_RATE":"80","COMMENT_LINES_DENSITY":"16.4","ROKR_ANA":"16.6666666666667","ROK_CHA":"1","ITS_AUTH_3M":"104","NCC_REU_IDX":"0.0902255639097744","SCM_COMMITS_3M":"163","FUNCTION_COMPLEXITY":"3.1","ROK_REL":"16"},"version":"Generated by the dashboard - Fri Sep 11 01:23:36 2015"}