{"name":"Metrics for project tools.cdt","children":{"ROKR_REL":"59.2592592592593","MLS_DEV_RESP_TIME_MED_3M":"0.08","SCM_COMMITTERS_3M":"14","SCM_COMMITTED_FILES_3M":"1257","RKO_CHA":"7","ITS_UPDATES_3M":"448","SCM_STABILITY_3M":"1.3","NCC_REU_IDX":"0.0899357601713062","RKO_ANA":"10","RKO_REL":"11","NCC_REU":"84","ROKR_REU":"25","ITS_BUGS_DENSITY":"18.43","FUNCTIONS":"73889","MLS_DEV_VOL_3M":"369","ITS_FIX_MED_3M":"2.08","IS_FB_OK":"1","TEST_SUCCESS_DENSITY":"100","NCC_ANA":"6566","MLS_USR_VOL_3M":"134","ROK_ANA":"2","NCC_CHA":"4442","ROKR":"44.2622950819672","TST_VOL_IDX":"0.771543836745176","LINE_COVERAGE":"36.4","RKO_REU":"3","BRANCH_COVERAGE":"34.8","FUNCTION_COMPLEXITY":"3.1","PUB_SCM_INFO_PMI":"5","NCC_ANA_IDX":"7.02997858672377","NCC_CHA_IDX":"4.7558886509636","RULES_ANA":"12","NCC":"10822","NCLOC":"934490","NCC_REL_IDX":"2.38758029978587","MLS_USR_RESP_TIME_MED_3M":"0.13","ROKR_ANA":"16.6666666666667","COMPLEXITY":"230370","ROK_REU":"1","PUBLIC_API":"42521","MLS_USR_AUTH_3M":"13","MKT_INSTALL_SUCCESS_1M":"3164","IS_PMD_OK":"1","ROK_CHA":"1","PLAN_REVIEWS_SUCCESS_RATE":"100","DUPLICATED_LINES":"116921","COMMENT_LINES_DENSITY":"16.3","ROKR_CHA":"12.5","PUB_ITS_INFO_PMI":"5","ITS_AUTH_3M":"54","MLS_DEV_SUBJ_3M":"102","ROK_REL":"16","DUPLICATED_LINES_DENSITY":"8.1","RULES_CHA":"8","UNCOVERED_LINES":"335528","RULES_REL":"27","MLS_DEV_RESP_RATIO_3M":"2.54","NCC_REL":"2230","RULES_REU":"4","SCM_COMMITS_3M":"188","MLS_USR_SUBJ_3M":"3","ITS_BUGS_OPEN":"4638","RULES":"61","PLAN_MILESTONES_VOL":"0","MLS_DEV_AUTH_3M":"41","MKT_FAV":"15","TESTS":"721","MLS_USR_RESP_RATIO_3M":"27"},"version":"Generated by the dashboard - Tue Dec  1 01:19:12 2015"}