{"version":"Generated by the dashboard - Sat Dec 19 01:20:58 2015","name":"Metrics for project tools.cdt","children":{"TESTS":"721","MLS_DEV_AUTH_3M":"41","ITS_BUGS_OPEN":"4638","RULES_REU":"4","DUPLICATED_LINES_DENSITY":"8.1","ROK_REU":"1","RKO_CHA":"7","PLAN_MILESTONES_VOL":"0","SCM_COMMITTERS_3M":"14","NCC_REU":"84","NCC":"10846","MLS_DEV_RESP_TIME_MED_3M":"0.08","RKO_REU":"3","FUNCTION_COMPLEXITY":"3.1","NCLOC":"934490","ITS_AUTH_3M":"54","COMPLEXITY":"230370","MKT_FAV":"15","ROKR_ANA":"16.6666666666667","ROKR_REL":"59.2592592592593","BRANCH_COVERAGE":"34.8","MLS_USR_RESP_TIME_MED_3M":"0.13","ROK_REL":"16","MLS_DEV_RESP_RATIO_3M":"2.54","TST_VOL_IDX":"0.771543836745176","UNCOVERED_LINES":"335528","NCC_ANA_IDX":"7.05460385438972","MLS_USR_VOL_3M":"134","ITS_BUGS_DENSITY":"18.43","ROKR":"44.2622950819672","NCC_REL":"2232","MLS_USR_AUTH_3M":"13","ROK_CHA":"1","PUB_SCM_INFO_PMI":"5","DUPLICATED_LINES":"116921","MLS_DEV_VOL_3M":"369","ROKR_CHA":"12.5","SCM_COMMITS_3M":"188","TEST_SUCCESS_DENSITY":"100","RULES_ANA":"12","ROKR_REU":"25","COMMENT_LINES_DENSITY":"16.3","FUNCTIONS":"73889","MLS_DEV_SUBJ_3M":"102","SCM_STABILITY_3M":"1.3","NCC_ANA":"6589","LINE_COVERAGE":"36.4","IS_FB_OK":"1","PLAN_REVIEWS_SUCCESS_RATE":"100","PUB_ITS_INFO_PMI":"5","IS_PMD_OK":"1","RULES":"61","MLS_USR_RESP_RATIO_3M":"27","NCC_REL_IDX":"2.38972162740899","RKO_ANA":"10","ITS_UPDATES_3M":"448","NCC_REU_IDX":"0.0899357601713062","NCC_CHA":"4453","RULES_REL":"27","MLS_USR_SUBJ_3M":"3","PUBLIC_API":"42521","MKT_INSTALL_SUCCESS_1M":"3164","SCM_COMMITTED_FILES_3M":"1257","RKO_REL":"11","RULES_CHA":"8","NCC_CHA_IDX":"4.76766595289079","ROK_ANA":"2","ITS_FIX_MED_3M":"2.08"}}