{"children":{"UNCOVERED_LINES":"30070","PUB_SCM_INFO_PMI":"5","MLS_USR_RESP_RATIO_3M":"1","SCM_COMMITTED_FILES_3M":"839","PLAN_REVIEWS_SUCCESS_RATE":"40","DUPLICATED_LINES":"6104","NCC_CHA_IDX":"1.99180327868852","ROK_ANA":"5","MLS_USR_SUBJ_3M":"1","NCC_REL_IDX":"0.540983606557377","MLS_USR_AUTH_3M":"1","MLS_DEV_VOL_3M":"143","MLS_DEV_RESP_TIME_MED_3M":"0.26","ROKR":"19.672131147541","ROKR_REU":"75","IS_FB_OK":"1","ROK_CHA":"4","ROKR_REL":"85.1851851851852","NCC_REL":"66","ROK_REL":"23","PLAN_MILESTONES_VOL":"0","MLS_USR_VOL_3M":"2","NCLOC":"122513","NCC_REU":"7","SCM_STABILITY_3M":"1.36","MLS_DEV_RESP_RATIO_3M":"2.89","NCC_REU_IDX":"0.0573770491803279","RKO_CHA":"4","ITS_UPDATES_3M":"106","ITS_BUGS_DENSITY":"1.8","RULES":"61","RULES_REU":"4","BRANCH_COVERAGE":"45","ROKR_ANA":"41.6666666666667","DUPLICATED_LINES_DENSITY":"2.7","NCC":"760","SCM_COMMITS_3M":"251","ITS_AUTH_3M":"11","RULES_REL":"27","PUBLIC_API":"5223","NCC_CHA":"243","LINE_COVERAGE":"56.2","COMMENT_LINES_DENSITY":"25.6","ITS_BUGS_OPEN":"143","MLS_DEV_SUBJ_3M":"37","COMPLEXITY":"28179","RULES_CHA":"8","NCC_ANA_IDX":"5.63114754098361","MLS_DEV_AUTH_3M":"14","RULES_ANA":"12","SCM_COMMITTERS_3M":"10","FUNCTIONS":"9082","IS_PMD_OK":"1","RKO_REL":"4","RKO_ANA":"7","ITS_FIX_MED_3M":"5.09","FUNCTION_COMPLEXITY":"3.1","ROKR_CHA":"50","NCC_ANA":"687","RKO_REU":"1","ROK_REU":"3","PUB_ITS_INFO_PMI":"5"},"version":"Generated by the dashboard - Sat Sep 12 01:19:06 2015","name":"Metrics for project tools.tracecompass"}